image_segmenter/__init__.py
image_segmenter/image_segmenter.py
image_segmenter/voc_writer.py
image_segmenter-0.2.1.dist-info/LICENSE
image_segmenter-0.2.1.dist-info/WHEEL
image_segmenter-0.2.1.dist-info/METADATA
image_segmenter-0.2.1.dist-info/RECORD
