Metadata-Version: 2.1
Name: image_segmenter
Version: 0.2.1
Summary: Image Segmenter
Author-email: Rich Baird <rich@rbaird.me>
Classifier: License :: OSI Approved :: MIT License
Project-URL: Home, https://github.com/richbai90/image_segmenter.git
Project-URL: Repository, https://github.com/richbai90/image_segmenter.git
